{
  "id": "admin-overview-shell",
  "name": "admin-overview-shell",
  "title": "Build admin overview shell with mock metrics",
  "description": "",
  "status": "planning",
  "dev_type": null,
  "scope": null,
  "package": null,
  "priority": "P2",
  "creator": "yuchao.he",
  "assignee": "yuchao.he",
  "createdAt": "2026-06-13",
  "completedAt": null,
  "branch": null,
  "base_branch": "main",
  "worktree_path": null,
  "commit": null,
  "pr_url": null,
  "subtasks": [],
  "children": [],
  "parent": "06-13-week1-trellis-setup",
  "relatedFiles": [],
  "notes": "",
  "meta": {}
}